Metadata-Version: 1.0
Name: y2z-distributions
Version: 0.5
Summary: Gaussian and Binomail distributions
Home-page: UNKNOWN
Author: Wisdom Chibeze
Author-email: nwachukwuchibeze29@outlook.com
License: UNKNOWN
Platform: UNKNOWN
